setup.cfg
setup.py
bz2_rl/__init__.py
bz2_rl/bz2_rl.py
bz2_rl.egg-info/PKG-INFO
bz2_rl.egg-info/SOURCES.txt
bz2_rl.egg-info/dependency_links.txt
bz2_rl.egg-info/top_level.txt
bz2_rl.egg-info/zip-safe