Metadata-Version: 1.1
Name: bz2-rl
Version: 1.0.1
Summary: Helper class for processing large bzip2 compressed text files efficiently without high memory usage.
Home-page: https://github.com/msikma/bz2_rl
Author: Michiel Sikma
Author-email: michiel@sikma.org
License: MIT
Platform: UNKNOWN
Classifier: Intended Audience :: Developers
Classifier: License :: OSI Approved :: MIT License
Classifier: Programming Language :: Python :: 3.4
Classifier: Programming Language :: Python :: 3.5
